Metadata-Version: 2.1
Name: raylib-py-flat
Version: 3.7.0
Summary: Bring all of raylibpy into a single import
Home-page: https://github.com/adamlwgriffiths/raylibpy-flat/
Author: Adam Griffiths
Author-email: adam.lw.griffiths@gmail.com
License: BSD 3-Clause License
Platform: UNKNOWN
Classifier: Intended Audience :: Developers
Classifier: License :: OSI Approved :: BSD License
Classifier: Operating System :: OS Independent
Classifier: Programming Language :: Python
Classifier: Programming Language :: Python :: 3
Classifier: Topic :: Multimedia :: Graphics
Classifier: Topic :: Software Development :: Libraries :: Python Modules
Requires-Python: >=3.4
